Metadata-Version: 2.1
Name: MatQQ
Version: 0.0
Summary: MatQQ
Home-page: UNKNOWN
Author-email: aryatahlil@yahoo.com
License: UNKNOWN
Platform: UNKNOWN
Requires-Python: >=3.6, <3.12
